torchcomplex/__init__.py
torchcomplex/gn.py
torchcomplex/ln.py
torchcomplex/nn/__init__.py
torchcomplex/nn/functional.py
torchcomplex/nn/init.py
torchcomplex/nn/modules/__init__.py
torchcomplex/nn/modules/activation.py
torchcomplex/nn/modules/batchnorm.py
torchcomplex/nn/modules/conv.py
torchcomplex/nn/modules/dropout.py
torchcomplex/nn/modules/groupnorm.py
torchcomplex/nn/modules/layernorm.py
torchcomplex/nn/modules/linear.py
torchcomplex/nn/modules/pooling.py
torchcomplex/nn/modules/upsampling.py
torchcomplex/utils/__init__.py
torchcomplex/utils/signaltools.py
torchcomplex/utils/support_funcs.py
pytorch_complex-0.2.0.dist-info/LICENSE
pytorch_complex-0.2.0.dist-info/METADATA
pytorch_complex-0.2.0.dist-info/WHEEL
pytorch_complex-0.2.0.dist-info/RECORD
