Metadata-Version: 2.1
Name: pytorch-complex
Version: 0.2.0
Summary: PyTorch wrapper for complex-valued operations. Usage: Similar to PyTorch. For using the Complex features of this library, just change the regular torch imports with torchcomplex imports. For example: import torchcomplex.nn as nn instead of import torch.nn as nn Then, simply nn.Conv2d for both torch and torchcomplex, for 2D Convolution
License: MIT
Author: Soumick Chatterjee, PhD
Author-email: contact@soumick.com
Requires-Python: >=3.11,<4.0
Classifier: License :: OSI Approved :: MIT License
Classifier: Programming Language :: Python :: 3
Classifier: Programming Language :: Python :: 3.11
Requires-Dist: torch (>=2.7.1+cu118,<3.0.0)
Requires-Dist: torchaudio (>=2.7.1+cu118,<3.0.0)
Requires-Dist: torchvision (>=0.22.1+cu118,<0.23.0)
